quickcall_voiceover/__init__.py
quickcall_voiceover/cli.py
quickcall_voiceover/generator.py
quickcall_voiceover/backends/__init__.py
quickcall_voiceover/backends/base.py
quickcall_voiceover/backends/kokoro.py
quickcall_voiceover/backends/piper.py
quickcall_voiceover-0.2.0.dist-info/METADATA
quickcall_voiceover-0.2.0.dist-info/WHEEL
quickcall_voiceover-0.2.0.dist-info/entry_points.txt
quickcall_voiceover-0.2.0.dist-info/licenses/LICENSE
quickcall_voiceover-0.2.0.dist-info/RECORD
