Metadata-Version: 2.4
Name: quickcall-voiceover
Version: 0.2.0
Summary: Utility tool for creating voice-over audio assets for QuickCall videos
Project-URL: Homepage, https://github.com/quickcall-dev/quickcall-voiceover
Project-URL: Repository, https://github.com/quickcall-dev/quickcall-voiceover
Project-URL: Issues, https://github.com/quickcall-dev/quickcall-voiceover/issues
Author-email: Sagar Sarkale <hello@quickcall.dev>
License-Expression: Apache-2.0
License-File: LICENSE
Keywords: audio,kokoro,piper,quickcall,tts,voiceover
Classifier: Development Status :: 4 - Beta
Classifier: Intended Audience :: Developers
Classifier: License :: OSI Approved :: Apache Software License
Classifier: Programming Language :: Python :: 3
Classifier: Programming Language :: Python :: 3.10
Classifier: Programming Language :: Python :: 3.11
Classifier: Programming Language :: Python :: 3.12
Classifier: Topic :: Multimedia :: Sound/Audio :: Speech
Requires-Python: >=3.10
Requires-Dist: rich>=14.2.0
Provides-Extra: all
Requires-Dist: kokoro>=0.9.4; extra == 'all'
Requires-Dist: piper-tts>=1.3.0; extra == 'all'
Requires-Dist: soundfile>=0.12.0; extra == 'all'
Provides-Extra: kokoro
Requires-Dist: kokoro>=0.9.4; extra == 'kokoro'
Requires-Dist: soundfile>=0.12.0; extra == 'kokoro'
Provides-Extra: piper
Requires-Dist: piper-tts>=1.3.0; extra == 'piper'
